gdcmd/__init__.py
gdcmd/cli.py
gdcmd/keycloak.py
gdcmd/secrets.py
gdcmd/helm/__init__.py
gdcmd/helm/list_charts.py
gdcmd/helm/template.py
gdcmd/helm/validate.py
gdcmd/helm/values.py
gdcmd/helm/values_parser.py
gdcmd-0.2.41.dist-info/METADATA
gdcmd-0.2.41.dist-info/WHEEL
gdcmd-0.2.41.dist-info/entry_points.txt
gdcmd-0.2.41.dist-info/RECORD
