Metadata-Version: 2.4
Name: gdcmd
Version: 0.2.41
Summary: Griddot packages
Author-email: Griddot <info@griddot.net>
Classifier: Intended Audience :: Developers
Classifier: Natural Language :: English
Requires-Python: >=3.12
Requires-Dist: click
Requires-Dist: cryptography
Requires-Dist: deepmerge
Requires-Dist: pydantic
Requires-Dist: pytest>=8.3.5
Requires-Dist: pyyaml
Requires-Dist: requests>=2.32.3
Requires-Dist: ruamel-yaml
Provides-Extra: dev
Requires-Dist: pytest; extra == 'dev'
